timbertrek/.DS_Store
timbertrek/__init__.py
timbertrek/timbertrek.js
timbertrek/timbertrek.py
timbertrek/__pycache__/__init__.cpython-37.pyc
timbertrek/__pycache__/__init__.cpython-39.pyc
timbertrek/__pycache__/timbertrek.cpython-37.pyc
timbertrek/__pycache__/timbertrek.cpython-39.pyc
timbertrek-0.1.7.dist-info/METADATA
timbertrek-0.1.7.dist-info/WHEEL
timbertrek-0.1.7.dist-info/top_level.txt
timbertrek-0.1.7.dist-info/RECORD
